README.md
setup.py
auth_methods/__init__.py
auth_methods/kubernetes.py
auth_methods/token.py
olympus_vault_client/__init__.py
olympus_vault_client/olympus_vault_client.py
olympus_vault_client.egg-info/PKG-INFO
olympus_vault_client.egg-info/SOURCES.txt
olympus_vault_client.egg-info/dependency_links.txt
olympus_vault_client.egg-info/requires.txt
olympus_vault_client.egg-info/top_level.txt