Metadata-Version: 2.1
Name: olympus-vault-client
Version: 0.0.8
Summary: vault client package for Databricks and Chimera
Home-page: https://gitlab.myteksi.net/olympus/olympus-vault-client
Author: olympus
